LICENSE
MANIFEST.in
README.md
requirements.txt
setup.cfg
setup.py
rectif_ai.egg-info/PKG-INFO
rectif_ai.egg-info/SOURCES.txt
rectif_ai.egg-info/dependency_links.txt
rectif_ai.egg-info/requires.txt
rectif_ai.egg-info/top_level.txt
rectifai/__init__.py
rectifai/settings.py
rectifai/version.py
rectifai/__pycache__/__init__.cpython-37.pyc
rectifai/__pycache__/settings.cpython-37.pyc
rectifai/__pycache__/version.cpython-37.pyc
rectifai/data/__init__.py
rectifai/data/__pycache__/__init__.cpython-37.pyc
rectifai/data/dataset/posturenet.py
rectifai/data/dataset/__pycache__/posturenet.cpython-37.pyc
rectifai/models/__init__.py
rectifai/models/__pycache__/__init__.cpython-37.pyc
rectifai/models/posenet/__init__.py
rectifai/models/posenet/decode.py
rectifai/models/posenet/network.py
rectifai/models/posenet/settings.py
rectifai/models/posenet/__pycache__/__init__.cpython-37.pyc
rectifai/models/posenet/__pycache__/decode.cpython-37.pyc
rectifai/models/posenet/__pycache__/network.cpython-37.pyc
rectifai/models/posenet/__pycache__/settings.cpython-37.pyc
rectifai/models/posturenet/__init__.py
rectifai/models/posturenet/config.py
rectifai/models/posturenet/network.py
rectifai/models/posturenet/__pycache__/__init__.cpython-37.pyc
rectifai/models/posturenet/__pycache__/config.cpython-37.pyc
rectifai/models/posturenet/__pycache__/network.cpython-37.pyc
rectifai/predictors/__init__.py
rectifai/predictors/demo_webcam.py
rectifai/predictors/__pycache__/__init__.cpython-37.pyc
rectifai/predictors/__pycache__/demo_webcam.cpython-37.pyc
rectifai/services/__init__.py
rectifai/tests/__init__.py
rectifai/tools/__init__.py
rectifai/tools/__pycache__/__init__.cpython-37.pyc
rectifai/tools/__pycache__/utils_posenet.cpython-37.pyc
rectifai/tools/utils/__init__.py
rectifai/tools/utils/posenet.py
rectifai/tools/utils/__pycache__/__init__.cpython-37.pyc
rectifai/tools/utils/__pycache__/posenet.cpython-37.pyc
rectifai/train/__init__.py
rectifai/train/metric_tracker.py
rectifai/train/posturenet.py
rectifai/train/tensorboard_writer.py
rectifai/train/trainer.py
rectifai/train/util.py
rectifai/train/__pycache__/__init__.cpython-37.pyc
