Metadata-Version: 2.1
Name: rectif-ai
Version: 0.1
Summary: Rectif.ai
Home-page: https://github.com/Sushil-Thapa/PyTorch-Hackathon-2019.git
Author: Sushil Thapa
Author-email: mailsushilthapa@gmail.com
License: UNKNOWN
Platform: UNKNOWN
Classifier: Programming Language :: Python :: 3
Classifier: Operating System :: OS Independent
